ochre_gym/__init__.py
ochre_gym/log.py
ochre_gym/ochre_env.py
ochre_gym/buildings/defaults.toml
ochre_gym/buildings/basic-v0/G0600650.ddy
ochre_gym/buildings/basic-v0/G0600650.epw
ochre_gym/buildings/basic-v0/home.xml
ochre_gym/buildings/basic-v0/schedules.csv
ochre_gym/buildings/bldg0000001/G0600650.epw
ochre_gym/buildings/bldg0000001/home.xml
ochre_gym/buildings/bldg0000001/schedules.csv
ochre_gym/buildings/bldg0000002/G1200110.epw
ochre_gym/buildings/bldg0000002/home.xml
ochre_gym/buildings/bldg0000002/schedules.csv
ochre_gym/buildings/bldg0000003/G1200050.epw
ochre_gym/buildings/bldg0000003/home.xml
ochre_gym/buildings/bldg0000003/schedules.csv
ochre_gym/buildings/bldg0000004/G0400130.epw
ochre_gym/buildings/bldg0000004/home.xml
ochre_gym/buildings/bldg0000004/schedules.csv
ochre_gym/buildings/bldg0000005/G1301770.epw
ochre_gym/buildings/bldg0000005/home.xml
ochre_gym/buildings/bldg0000005/schedules.csv
ochre_gym/buildings/bldg0000006/G0600950.epw
ochre_gym/buildings/bldg0000006/home.xml
ochre_gym/buildings/bldg0000006/schedules.csv
ochre_gym/buildings/bldg0000007/G0600010.epw
ochre_gym/buildings/bldg0000007/home.xml
ochre_gym/buildings/bldg0000007/schedules.csv
ochre_gym/buildings/bldg0000008/G4700930.epw
ochre_gym/buildings/bldg0000008/home.xml
ochre_gym/buildings/bldg0000008/schedules.csv
ochre_gym/buildings/bldg0000009/G4001390.epw
ochre_gym/buildings/bldg0000009/home.xml
ochre_gym/buildings/bldg0000009/schedules.csv
ochre_gym/buildings/bldg0000010/G5300330.epw
ochre_gym/buildings/bldg0000010/home.xml
ochre_gym/buildings/bldg0000010/schedules.csv
ochre_gym/buildings/bldg0000011/G4200110.epw
ochre_gym/buildings/bldg0000011/home.xml
ochre_gym/buildings/bldg0000011/schedules.csv
ochre_gym/buildings/bldg0000012/G0800590.epw
ochre_gym/buildings/bldg0000012/home.xml
ochre_gym/buildings/bldg0000012/schedules.csv
ochre_gym/buildings/bldg0000013/G5501050.epw
ochre_gym/buildings/bldg0000013/home.xml
ochre_gym/buildings/bldg0000013/schedules.csv
ochre_gym-0.1.0a1.dist-info/LICENSE
ochre_gym-0.1.0a1.dist-info/METADATA
ochre_gym-0.1.0a1.dist-info/WHEEL
ochre_gym-0.1.0a1.dist-info/top_level.txt
ochre_gym-0.1.0a1.dist-info/RECORD
