Metadata-Version: 2.1
Name: ochre-gym
Version: 0.1.0a1
Summary: A Gymnasium environment based on the purely Python-based OCHRE residential energy building simulator.
Home-page: https://github.nrel.gov/NREL/ochre_gym
Author: Patrick Emami, Xiangyu Zhang, Peter Graf
Author-email: pemami@nrel.gov, Xiangyu.Zhang@nrel.gov, Peter.Graf@nrel.gov
License: BSD 3-Clause
Keywords: reinforcement learning,hvac,building,building energy simulation
Classifier: Development Status :: 3 - Alpha
Classifier: Intended Audience :: Science/Research
Classifier: License :: OSI Approved :: BSD License
Classifier: Natural Language :: English
Classifier: Programming Language :: Python :: 3
Classifier: Topic :: Scientific/Engineering :: Artificial Intelligence
Requires-Python: >=3.9
License-File: LICENSE
Requires-Dist: gymnasium ==0.28.1
Requires-Dist: tomli ==2.0.1
Requires-Dist: ochre-nrel ==0.8.4
